python3D/__init__.py
python3D/main.py
python3d-2024.1.3.dist-info/METADATA
python3d-2024.1.3.dist-info/WHEEL
python3d-2024.1.3.dist-info/licenses/LICENSE
python3d-2024.1.3.dist-info/RECORD
