Metadata-Version: 2.4
Name: python3D
Version: 2024.1.3
Summary: p3D is a pythonic 3D engine that can simulate textured OBJ models. p3D features logs, preferences, customization, and simple code structure.
Project-URL: Homepage, https://github.com/aaravdave/p3D
Project-URL: Issues, https://github.com/aaravdave/p3D/issues
Author-email: Aarav Dave <aaravhdave@gmail.com>
License-File: LICENSE
Keywords: 3D,3D engine,engine,game,game engine,p3D,py3D,python3D
Classifier: License :: OSI Approved :: MIT License
Classifier: Operating System :: OS Independent
Classifier: Programming Language :: Python :: 3
Requires-Python: >=3.9
Requires-Dist: numba
Requires-Dist: numpy
Requires-Dist: pygame>1.9.4
Requires-Dist: scipy
